{"2":{"order":0,"title":"Bisagra rota","description":"Se informa a cliente y acepta cambio","budget":"2000","createdAt":1624546985,"updatedAt":1624546985,"_id":2,"id":2},"3":{"order":15,"title":"Reparaci\u00f3n de bios","description":"","budget":"1500","createdAt":1624555445,"updatedAt":1624555445,"_id":3,"id":3},"5":{"order":10,"title":"Una actualizaci\u00f3n","description":"","budget":"1000","createdAt":1624556275,"updatedAt":1624556275,"_id":5,"id":5},"__metadata":{"nextKey":6,"lastInsertedKey":5}}